umnet_db/__init__.py
umnet_db/cli/__init__.py
umnet_db/cli/activity_query.py
umnet_db/cli/db_delete.py
umnet_db/cli/db_init.py
umnet_db/cli/table_query.py
umnet_db/cli/utils.py
umnet_db/errors.py
umnet_db/models.py
umnet_db/queries.py
umnet_db/utils.py
umnet_db-0.5.1.dist-info/METADATA
umnet_db-0.5.1.dist-info/WHEEL
umnet_db-0.5.1.dist-info/entry_points.txt
umnet_db-0.5.1.dist-info/RECORD
