Metadata-Version: 2.3
Name: umnet-db
Version: 0.5.1
Summary: Custom database for storing network data
License: MIT
Author: Amy Liebowitz
Author-email: amylieb@umich.edu
Requires-Python: >=3.10
Classifier: License :: OSI Approved :: MIT License
Classifier: Programming Language :: Python :: 3
Classifier: Programming Language :: Python :: 3.10
Classifier: Programming Language :: Python :: 3.11
Classifier: Programming Language :: Python :: 3.12
Classifier: Programming Language :: Python :: 3.13
Requires-Dist: netaddr (>=1.3.0)
Requires-Dist: postgresql-audit (>=0.17.1)
Requires-Dist: psycopg (>=3.2.6)
Requires-Dist: psycopg-binary (>=3.2.6)
Requires-Dist: python-decouple (>=3.8)
Requires-Dist: sqlalchemy (>=2.0.24)
Requires-Dist: texttable (>=1.7.0)
